README.md
setup.cfg
setup.py
distr_upload1/Binomialdistribution.py
distr_upload1/Gaussiandistribution.py
distr_upload1/Generaldistribution.py
distr_upload1/__init__.py
distr_upload1.egg-info/PKG-INFO
distr_upload1.egg-info/SOURCES.txt
distr_upload1.egg-info/dependency_links.txt
distr_upload1.egg-info/not-zip-safe
distr_upload1.egg-info/top_level.txt